{
  "jadwal": [
    {
      "tanggal": "Senin 03 Nov 2025",
      "ruang": "R. 1H",
      "ujian": [
        {
          "matkul": "Etika Profesi dan Pendidikan Anti Korupsi",
          "jam":"00.00 - 00.00",
          "dosen": "Kurniawan Wahyu Haryanto, S.Kom, M.MT"
        },
        {
          "matkul": "Pemrograman Web Lanjut",
          "dosen": "Mukhamad Fatkhur Roji, M.Kom"
        }
      ]
    },
    {
      "tanggal": "Selasa 04 Nov 2025",
      "ruang": "R. 1L",
      "ujian": [
        {
          "matkul": "Pemrograman Mobile Lanjut",
          "dosen": "Abdul Rokhim, M.Kom"
        },
        {
          "matkul": "tidak ada ujian",
          "dosen": "tidak ada ujian"
        }
      ]
    },
    {
      "tanggal": "Rabu 05 Nov 2025",
      "ruang": "R. T",
      "ujian": [
        {
          "matkul": "Riset IT",
          "dosen": "Erri Wahyu Puspitarini, S.Kom, M.MT"
        },
        {
          "matkul": "tidak ada ujian",
          "dosen": "tidak ada ujian"
        }
      ]
    },
    {
      "tanggal": "Kamis 06 Nov 2025",
      "ruang": "R. T",
      "ujian": [
        {
          "matkul": "Pendidikan Agama",
          "dosen": "Abu Nasir, M.Ag"
        },
        {
          "matkul": "tidak ada ujian",
          "dosen": "tidak ada ujian"
        }
      ]
    },
    {
      "tanggal": "Jumat 07 Nov 2025",
      "ruang": "R. 1 F",
      "ujian": [
        {
          "matkul": "Proyek Perangkat Lunak",
          "dosen": "Prof. Dr. Saiful Bukhori, ST., M.Kom"
        },
        {
          "matkul": "tidak ada ujian",
          "dosen": "tidak ada ujian"
        }
      ]
    }
  ]
}